<?xml version="1.0"?>
<PresetGroup xmlns:xsi="http://www.w3.org/2001/XMLSchema-instance" xmlns:xsd="http://www.w3.org/2001/XMLSchema" Label="Play Piano">
  <Preset Label="Serenade (self_Social_SingingSerenade_Piano)" Value="150455" />
  <Preset Label="Sing Songs (piano_Sing_Song)" Value="138595" />
  <Preset Label="Write Lyrics (singingSkill_StartWriting_Piano)" Value="139819" />
  <Preset Label="Sing Serenade (piano_Picker_SingingSerenade)" Tags="TestUnsafe" Value="150449" />
  <Preset Label="piano_WriteLyrics_Staging" Value="139762" />
  <Preset Label="piano_WriteLyrics" Value="139748" />
  <Preset Label="Play with Emotion (piano_Concerto_PlayAwayFeelings)" Value="161870" />
  <Preset Label="Serenade (piano_Social_Serenade)" Value="13812" />
  <Preset Label="Play Concerto (piano_Concerto)" Value="13797" />
  <Preset Label="Jazz Up the Place (piano_Jazz_Up_Crowd)" Value="13799" />
  <Preset Label="Write Jingle (piano_WriteJingle)" Value="33779" />
  <Preset Label="Plunk for Inspiration (piano_PlunkForInspiration)" Value="36012" />
  <Preset Label="Practice (piano_Practice)" Value="13809" />
  <Preset Label="Practice (piano_Practice_Child)" Value="37969" />
  <Preset Label="Practice (piano_Practice_Child_Scales)" Value="75872" />
  <Preset Label="Practice (piano_Practice_Scales)" Value="75835" />
  <Preset Label="Tickle the Ivories (piano_TickleTheIvories)" Value="34476" />
  <Preset Label="Tickle the Ivories (piano_TickleTheIvories_Scales)" Value="75866" />
  <Preset Label="Carol of Cleaning (piano_Carol_Of_Cleaning)" Value="28082" />
  <Preset Label="Ditty of Drowsiness (piano_Ditty_Of_Drowsiness)" Value="28060" />
  <Preset Label="Etude of Egress (piano_Etude_Of_Egress)" Value="28085" />
  <Preset Label="Melody of Mealtime (piano_Melody_Of_Mealtime)" Value="28089" />
  <Preset Label="Song of Sophistication (piano_Song_Of_Sophistication)" Value="28093" />
  <Preset Label="Play (piano_Play_Song)" Value="13808" />
  <Preset Label="Listen to Serenade (piano_Social_Listen_Serenade)" Value="38736" />
  <Preset Label="Tickle the Ivories (piano_TickleTheIvories_Chooser)" Value="75867" />
  <Preset Label="Practice (piano_Practice_Chooser)" Value="75853" />
  <Preset Label="Practice (piano_Practice_Child_Chooser)" Value="75875" />
  <Preset Label="Write Jingle (piano_WriteJingle)" Value="33779" />
  <Preset Label="Practice (portableKeyboard_Practice)" Value="144737" />
  <Preset Label="Practice (portableKeyboard_Practice_Child)" Value="144738" />
  <Preset Label="Plunk for Inspiration (portableKeyboard_Practice_PlunkForInspiration)" Value="144743" />
  <Preset Label="Practice (portableKeyboard_Practice_Scales)" Value="144739" />
  <Preset Label="Practice (portableKeyboard_Practice_Scales_Child)" Value="144740" />
  <Preset Label="Tickle the Ivories (portableKeyboard_Practice_TickleTheIvories)" Value="144741" />
  <Preset Label="Tickle the Ivories (portableKeyboard_Practice_TickleTheIvories_Scales)" Value="144742" />
  <Preset Label="Write Jingle (portableKeyboard_WriteJingle)" Value="144733" />
  <Preset Label="Jazz Up the Place (portableKeyboard_JazzUpCrowd)" Value="144730" />
  <Preset Label="Play Concerto (portableKeyboard_Concerto)" Value="144732" />
  <Preset Label="Song of Sophistication (portableKeyboard_SongOfSophistication)" Value="144750" />
  <Preset Label="Melody of Mealtime (portableKeyboard_MelodyOfMealtime)" Value="144749" />
  <Preset Label="Etude of Egress (portableKeyboard_EtudeOfEgress)" Value="144748" />
  <Preset Label="Ditty of Drowsiness (portableKeyboard_DittyOfDrowsiness)" Value="144747" />
  <Preset Label="Carol of Cleaning (portableKeyboard_CarolOfCleaning)" Value="144746" />
  <Preset Label="Write Lyrics (singingSkill_StartWriting_PortableKeyboard)" Value="150336" />
  <Preset Label="portableKeyboard_WriteLyrics_Staging" Value="150334" />
  <Preset Label="portableKeyboard_WriteSong_Staging" Value="150335" />
  <Preset Label="Serenade (portableKeyboard_Picker_Serenade)" Tags="TestUnsafe" Value="144744" />
  <Preset Label="Sing Serenade (portableKeyboard_Picker_SingingSerenade)" Tags="TestUnsafe" Value="150394" />
  <Preset Label="Serenade (portableKeyboard_Social_Serenade)" Value="144729" />
  <Preset Label="Serenade (self_Social_SingingSerenade_PortableKeyboard)" Value="150393" />
  <Preset Label="Practice (portableKeyboard_Practice_Chooser)" Value="144752" />
  <Preset Label="Practice (portableKeyboard_Practice_Chooser_Child)" Value="144753" />
  <Preset Label="Tickle the Ivories (portableKeyboard_Practice_Chooser_TickleTheIvories)" Value="144754" />
  <Preset Label="Play (portableKeyboard_Play_Song)" Value="144449" />
  <Preset Label="Sing Songs (portableKeyboard_Sing_Song)" Value="150267" />
</PresetGroup>