<?xml version="1.0"?>
<PresetGroup xmlns:xsi="http://www.w3.org/2001/XMLSchema-instance" xmlns:xsd="http://www.w3.org/2001/XMLSchema" Label="Fight">
  <Preset Label="Fight Vampire (mixer_social_Fight_targeted_mean_SimAndVampire_Duel_DarkForm_WithGarlic)" Tags="TestUnsafe" Value="152682" />
  <Preset Label="Fight Vampire (mixer_social_Fight_targeted_mean_SimAndVampire_Duel_WithGarlic)" Tags="TestUnsafe" Value="150766" />
  <Preset Label="Vampiric Duel (mixer_social_VampiricDuel_Targeted_Mean_VampireToVampire_ActorOnlyDarkForm)" Tags="TestUnsafe" Value="152647" />
  <Preset Label="Vampiric Duel (mixer_social_VampiricDuel_Targeted_Mean_VampireToVampire)" Tags="TestUnsafe" Value="150919" />
  <Preset Label="Fight Vampire (mixer_social_Fight_targeted_mean_SimAndVampire_Duel_DarkForm_WithoutGarlic)" Tags="TestUnsafe" Value="152688" />
  <Preset Label="Fight Vampire (mixer_social_Fight_targeted_mean_SimAndVampire_Duel_WithoutGarlic)" Tags="TestUnsafe" Value="150767" />
  <Preset Label="Vampiric Duel (mixer_social_VampiricDuel_Targeted_Mean_VampireToVampire_ActorTargetDarkForm)" Tags="TestUnsafe" Value="152650" />
  <Preset Label="Vampiric Duel (mixer_social_VampiricDuel_Targeted_Mean_VampireToVampire_TargetOnlyDarkForm)" Tags="TestUnsafe" Value="152649" />
  <Preset Label="Fight {1.SimName} (mixer_social_Fight_targeted_mean_VampireAndSim_Duel_WithGarlic)" Tags="TestUnsafe" Value="150768" />
  <Preset Label="Fight {1.SimName} (mixer_social_Fight_targeted_mean_VampireAndSim_Duel_DarkForm_WithGarlic)" Tags="TestUnsafe" Value="152676" />
  <Preset Label="Fight {1.SimName} (mixer_social_Fight_targeted_mean_VampireAndSim_Duel_DarkForm_WithoutGarlic)" Tags="TestUnsafe" Value="152678" />
  <Preset Label="Fight {1.SimName} (mixer_social_Fight_targeted_mean_VampireAndSim_Duel_WithoutGarlic)" Tags="TestUnsafe" Value="150769" />
  <Preset Label="Vampiric Spar (mixer_Social_VampiricSpar_Targeted_Friendly)" Tags="TestUnsafe" Value="154300" />
  <Preset Label="Vampiric Spar (mixer_Social_VampiricSpar_Targeted_Friendly_ActorOnlyDarkForm)" Tags="TestUnsafe" Value="154304" />
  <Preset Label="Vampiric Spar (mixer_Social_VampiricSpar_Targeted_Friendly_ActorTargetDarkForm)" Tags="TestUnsafe" Value="154316" />
  <Preset Label="Vampiric Spar (mixer_Social_VampiricSpar_Targeted_Friendly_TargetOnlyDarkForm)" Tags="TestUnsafe" Value="154323" />
  <Preset Label="Argue about Arguing (mixer_Argument_Start_Arguments)" Tags="TestUnsafe" Value="160018" />
  <Preset Label="Argue about Career (mixer_Argument_Start_Careers)" Tags="TestUnsafe" Value="160006" />
  <Preset Label="Argue about Children (mixer_Argument_Start_Children)" Tags="TestUnsafe" Value="160026" />
  <Preset Label="Argue about Cleanliness (mixer_Argument_Start_Cleanliness)" Tags="TestUnsafe" Value="160014" />
  <Preset Label="Argue about Exercising (mixer_Argument_Start_Exercising)" Tags="TestUnsafe" Value="160024" />
  <Preset Label="Argue about Food (mixer_Argument_Start_Food)" Tags="TestUnsafe" Value="160027" />
  <Preset Label="Argue about House Rules (mixer_Argument_Start_HouseRules)" Tags="TestUnsafe" Value="160022" />
  <Preset Label="Argue about Humor (mixer_Argument_Start_Humor)" Tags="TestUnsafe" Value="160011" />
  <Preset Label="Argue about Job (mixer_Argument_Start_Job)" Tags="TestUnsafe" Value="160020" />
  <Preset Label="Argue about Kindness (mixer_Argument_Start_Kindness)" Tags="TestUnsafe" Value="160010" />
  <Preset Label="Argue about Life Goals (mixer_Argument_Start_LifeGoals)" Tags="TestUnsafe" Value="160025" />
  <Preset Label="Argue about Outlook on Life (mixer_Argument_Start_LifeOutlook)" Tags="TestUnsafe" Value="160008" />
  <Preset Label="Argue about Morals (mixer_Argument_Start_Morals)" Tags="TestUnsafe" Value="160009" />
  <Preset Label="Argue about Music (mixer_Argument_Start_Music)" Tags="TestUnsafe" Value="160016" />
  <Preset Label="Argue about the Wonders of Nature (mixer_Argument_Start_NatureWonders)" Tags="TestUnsafe" Value="160013" />
  <Preset Label="Argue about Parenting (mixer_Argument_Start_Parenting)" Tags="TestUnsafe" Value="160021" />
  <Preset Label="Argue about Politics (mixer_Argument_Start_Politics)" Tags="TestUnsafe" Value="159361" />
  <Preset Label="Argue about Romance (mixer_Argument_Start_Romance)" Tags="TestUnsafe" Value="160015" />
  <Preset Label="Argue about School (mixer_Argument_Start_School)" Tags="TestUnsafe" Value="160019" />
  <Preset Label="Argue about Sharing (mixer_Argument_Start_Sharing)" Tags="TestUnsafe" Value="160017" />
  <Preset Label="Argue about Social Anxiety (mixer_Argument_Start_SocialAnxiety)" Tags="TestUnsafe" Value="160012" />
  <Preset Label="Argue about Who's Better (mixer_Argument_Start_WhosBetter)" Tags="TestUnsafe" Value="160023" />
  <Preset Label="Duel for Artifacts (socials_Targeted_MagicDuel_Start_Artifacts)" Tags="TestUnsafe" Value="217308" />
  <Preset Label="Friendly Duel (socials_Targeted_MagicDuel_Start_Friendly)" Tags="TestUnsafe" Value="217306" />
  <Preset Label="Heated Duel (socials_Targeted_MagicDuel_Start_Heated)" Tags="TestUnsafe" Value="217282" />
  <Preset Label="Duel for Ingredients (socials_Targeted_MagicDuel_Start_Items)" Tags="TestUnsafe" Value="217310" />
  <Preset Label="Duel for Knowledge (socials_Targeted_MagicDuel_Start_Knowledge)" Tags="TestUnsafe" Value="217312" />
  <Preset Label="Challenge to Duel for Artifacts (socials_Targeted_MagicDuel_Start_Artifacts_Challenge)" Tags="TestUnsafe" Value="217309" />
  <Preset Label="Challenge to Friendly Duel (socials_Targeted_MagicDuel_Start_Friendly_Challenge)" Tags="TestUnsafe" Value="217307" />
  <Preset Label="Challenge to Heated Duel (socials_Targeted_MagicDuel_Start_Heated_Challenge)" Tags="TestUnsafe" Value="217294" />
  <Preset Label="Challenge to Duel for Ingredients (socials_Targeted_MagicDuel_Start_Items_Challenge)" Tags="TestUnsafe" Value="217311" />
  <Preset Label="Challenge to Duel for Knowledge (socials_Targeted_MagicDuel_Start_Knowledge_Challenge)" Tags="TestUnsafe" Value="217313" />
  <Preset Label="Magic Duel (social_MagicDuel)" Value="216271" />
  <Preset Label="Magic Duel (social_MagicDuel_Heated)" Value="219664" />
  <Preset Label="Magic Duel (social_MagicDuel_Artifact)" Value="220233" />
  <Preset Label="Magic Duel (social_MagicDuel_Items)" Value="220235" />
  <Preset Label="Magic Duel (social_MagicDuel_Knowledge)" Value="220234" />
  <Preset Label="Magic Duel (social_MagicDuel_Listen)" Value="216272" />
  <Preset Label="Wrestle (mixer_social_Fight_targeted_mean_bear)" Tags="TestUnsafe" Value="108106" />
  <Preset Label="Practice Fighting (mixer_social_PracticeFighting_targeted_Friendly_alwaysOn_skills)" Tags="TestUnsafe" Value="28908" />
  <Preset Label="Fight Supreme Villain (mixer_social_FightSupervillain_targeted_mean_career)" Tags="TestUnsafe" Value="38775" />
  <Preset Label="Fight! (mixer_social_Fight_targeted_mean)" Tags="TestUnsafe" Value="26138" />
  <Preset Label="Try to Pick Fight (mixer_social_TryToPickFight_targeted_mean_middleScore_child)" Tags="TestUnsafe" Value="98912" />
  <Preset Label="mixer_TransitionToIntimate_BeAffectionate" Tags="TestUnsafe" Value="129376" />
  <Preset Label="Fight Father Winter for Presents! (mixer_social_Fight_targeted_mean_FatherWinter)" Tags="TestUnsafe" Value="187113" />
  <Preset Label="Fight Flower Bunny for Eggs! (mixer_social_Fight_targeted_mean_FlowerBunny)" Tags="TestUnsafe" Value="190096" />
  <Preset Label="Fight Paparazzi! (mixer_social_Fight_targeted_mean_Paparazzi)" Tags="TestUnsafe" Value="196391" />
  <Preset Label="Fight to Get Inside (social_VIPRope_Bouncer_Fight)" Value="191891" />
</PresetGroup>