<?xml version="1.0"?>
<PresetGroup xmlns:xsd="http://www.w3.org/2001/XMLSchema" xmlns:xsi="http://www.w3.org/2001/XMLSchema-instance" Label="All Situation Goals EP14">
  <Preset Label="Practice Hopscotch (whim_PracticeHopscotch)" Value="338695" />
  <Preset Label="Eat Potluck Food (Goal_NeighborhoodPotLuck_Eat)" Value="342079" />
  <Preset Label="Successfully Socialize with the Property Owner (whim_FearConfrontation_Eviction)" Value="342762" />
  <Preset Label="Compliment Potluck Item (Goal_NeighborhoodPotluck_Compliment)" Value="343234" />
  <Preset Label="Gossip with Sims (Goal_NeighborhoodPotluck_Gossip)" Value="343236" />
  <Preset Label="Clean Up (Goal_NeighborhoodPotluck_Clean)" Value="343237" />
  <Preset Label="Socialize while Swimming (Goal_PoolParty_SocializeWhileSwimming)" Value="343462" />
  <Preset Label="Socialize by Poolside (Goal_PoolParty_SocializePoolside)" Value="343463" />
  <Preset Label="Relax on a Float Lounger or Lounge Chair (Goal_PoolParty_RelaxInLounger)" Value="343466" />
  <Preset Label="Go Swimming (Goal_PoolParty_GoSwimming)" Value="343469" />
  <Preset Label="Socialize in the Hot Tub (goal_PoolParty_SocializeInHotTub)" Value="343470" />
  <Preset Label="Listen to Music in Hot Tub (Goal_PoolParty_ListenRadio)" Value="343471" />
  <Preset Label="Repair or Replace All Broken Electrical Objects (situationGoal_muEvent_Electrical)" Value="343474" />
  <Preset Label="Complain About Weather (goal_PoolParty_ComplainAboutWeather)" Value="343483" />
  <Preset Label="Repair or Replace All Broken Water Objects (situationGoal_muEvent_WaterLeak_Repair)" Value="343512" />
  <Preset Label="Replace the Faulty Stove, Oven, or Grill (situationGoal_muEvent_Explosion)" Value="343681" />
  <Preset Label="Deploy Blight Spray (situationGoal_muEvent_Blight_Spray)" Value="343790" />
  <Preset Label="Empty Trash (situationGoal_muEvent_TrashOverload_EmptyTrash)" Value="343923" />
  <Preset Label="Release a Sky Lantern (whim_ChildoftheSEA_ReleaseSkyLantern)" Value="344237" />
  <Preset Label="Eat Tomarani Cuisine (whim_ChildoftheSEA_EatRegionalFood)" Value="344238" />
  <Preset Label="Socialize with Close Sims (whim_ChildoftheSEA_SocializewithCloseSims)" Value="344239" />
  <Preset Label="Use Chemical Algae Destroyer (situationGoal_muEvent_Algae_PourChemical)" Value="344274" />
  <Preset Label="Swim to Clean Algae (situationGoal_muEvent_Algae_Swim)" Value="344275" />
  <Preset Label="Shop at the Night Market  (whim_ChildoftheSEA_VisitNightMarket)" Value="344425" />
  <Preset Label="Repair or Replace the Toilet (situationGoal_muEvent_SewageLeak_Repair)" Value="344644" />
  <Preset Label="Flush It Out (situationGoal_muEvent_SewageLeak_Flush)" Value="344645" />
  <Preset Label="Confront Ghost (situationGoal_muEvent_Haunting_Confront)" Value="344717" />
  <Preset Label="Exorcize the Ghost (situationGoal_muEvent_Haunting_Exorcize)" Value="344718" />
  <Preset Label="Promise Better Conditions To Your Tenants (situationGoal_muEvent_TenantRevolt_Promised)" Value="344846" />
  <Preset Label="Stomp the Bugs! (situationGoal_muEvent_Infestation_Stomp)" Value="345002" />
  <Preset Label="Deploy a Fumigation Device (situationGoal_muEvent_Infestation_Fumigate)" Value="345003" />
  <Preset Label="Destroy the Cursed Book (situationGoal_muEvent_Cursed_DestroyCurse)" Value="345150" />
  <Preset Label="Mail Away the Curse (situationGoal_muEvent_Cursed_MailCurse)" Value="345151" />
  <Preset Label="Scour for Memes (computer_intobj_NeighborTraits_LookForMemes)" Value="347926" />
  <Preset Label="Donate to a Cause (Whim_NeighborTraits_DonateToACause)" Value="347927" />
  <Preset Label="Snoop (Goal_NeighborTraits_Snoop)" Value="347930" />
  <Preset Label="Offer Wisdom (Goal_NeighborTraits_ShareLifeWisdom)" Value="347932" />
  <Preset Label="Play Marbles (whim_PlayMarbles)" Value="349330" />
  <Preset Label="Confront about Secret (Goal_NeighborTraits_ConfrontAboutSecret)" Value="349856" />
  <Preset Label="Write Gossip Blog Post (computer_intobj_NeighborTraits_WriteGossipBlog)" Value="349858" />
  <Preset Label="Learn a Secret (whim_NeighborTraits_LearnASecret)" Value="349860" />
  <Preset Label="Learn about a Sim (whim_NeighborTraits_LearnAboutSim)" Value="349862" />
  <Preset Label="Connect with Youths (whim_NeighborTraits_ConnectWithYouths)" Value="349864" />
  <Preset Label="Teach Lesson to Family (whim_NeighborTraits_TeachLesson)" Value="349866" />
  <Preset Label="Offer Generosity (whim_NeighborTraits_OfferGenerosity)" Value="349868" />
  <Preset Label="Complete Trash Removal (situationGoal_muEvent_TrashOverload_TrashDriveComplete)" Value="350679" />
  <Preset Label="Tend Community Garden (want_NeighborTraits_CommunityGarden)" Value="351391" />
  <Preset Label="Self-Actualize (want_NeighborTraits_SelfActualize)" Value="351393" />
  <Preset Label="Spout Memes (want_NeighborTraits_SpoutMemes)" Value="351394" />
  <Preset Label="Attend Social Event (want_NeighborTraits_AttendSocialEvent)" Value="351395" />
  <Preset Label="Neglect Tenants (whim_APM_NeglectTenants)" Value="351400" />
  <Preset Label="Give Away Simoleons (want_NeighborTraits_GiveAwaySimoleons)" Value="351479" />
  <Preset Label="Donate to Unit Event (whim_APM_SendDonation)" Value="351520" />
  <Preset Label="Solve Tenant Problems (whim_APM_SortOutTenantsProblems)" Value="351521" />
  <Preset Label="Roll Up Sleeves (whim_muEvent_TenantRollUpSleeves)" Value="351579" />
  <Preset Label="Call Your Property Owner and Ask For Better Conditions (situationGoal_muEvent_TenantRevolt_Requested)" Value="351767" />
  <Preset Label="Leave a Passive Aggressive Note (situationGoal_muEvent_Nuisance_LeaveNote)" Value="351862" />
  <Preset Label="Call Property Owner to Sort Out Neighbors (situationGoal_muEvent_Nuisance_CallOwner)" Value="351863" />
  <Preset Label="Mop Puddles (situationGoal_muEvent_WaterLeak_Mop)" Value="352233" />
  <Preset Label="lifeMilestoneGoal_Actor_FirstHopscotchWin" Value="352702" />
  <Preset Label="lifeMilestoneGoal_Actor_FirstMarbleWin" Value="352703" />
  <Preset Label="lifeMilestoneGoal_Actor_GotEvicted" Value="352704" />
  <Preset Label="lifeMilestoneGoal_Actor_FirstMoldExposure" Value="352705" />
  <Preset Label="lifeMilestoneGoal_IntObject_FirstBreakIn" Value="353293" />
  <Preset Label="Skip Paying Rent (whim_MultiUnit_SkipRent)" Value="353698" />
  <Preset Label="Spread the Cringe (buff_NeighborTraits_SpreadTheCringe)" Value="354724" />
  <Preset Label="Spread the Joy (buff_NeighborTraits_SpreadTheJoy)" Value="354725" />
  <Preset Label="lifeMilestoneGoal_IntObject_AdoptedTiger" Value="355064" />
  <Preset Label="Clean or Repair Something (situationGoal_muEvent_MaintenanceDay)" Value="356463" />
  <Preset Label="Call Guests to Meal (Goal_NeighborHoodPotluck_CallToMeal)" Value="356737" />
  <Preset Label="Donate to Charity (situationGoal_muEvent_Charity_MailDonation)" Value="357032" />
  <Preset Label="Uproot All Blighted Plants (situationGoal_muEvent_Blight_UprootAll)" Value="360298" />
</PresetGroup>