<?xml version="1.0"?>
<PresetGroup xmlns:xsi="http://www.w3.org/2001/XMLSchema-instance" xmlns:xsd="http://www.w3.org/2001/XMLSchema" Label="whimSet_EmotionBored">
  <Preset Label="Whim_WatchTV" Value="25921" />
  <Preset Label="Whim_ReadSomething" Value="35448" />
  <Preset Label="Whim_BuyChessBoard" Value="34366" />
  <Preset Label="Whim_BuyTV" Value="25632" />
  <Preset Label="Whim_PlayChess" Value="34353" />
  <Preset Label="Whim_BuyComputer" Value="34973" />
  <Preset Label="Whim_PlayComputerGame" Value="34376" />
  <Preset Label="Whim_BuyMotionGamingRig" Value="34398" />
  <Preset Label="Whim_ChatSim" Value="28010" />
  <Preset Label="Whim_TravelToMuseum" Value="38354" />
  <Preset Label="Whim_TravelToBar" Value="38366" />
  <Preset Label="Whim_TravelToClub" Value="38355" />
  <Preset Label="Whim_CallSim" Value="35727" />
  <Preset Label="Whim_SuggestFun_Bored" Value="39624" />
  <Preset Label="Whim_Lazy_TakeNap" Value="34836" />
  <Preset Label="Whim_CollectAnything" Value="39626" />
  <Preset Label="whim_DontWakeLlama_Play" Value="129498" />
  <Preset Label="whimGoal_WatchMovie" Value="129150" />
  <Preset Label="Whim_BlockConstructionTable_Build" Value="165790" />
</PresetGroup>