<?xml version="1.0"?>
<PresetGroup xmlns:xsd="http://www.w3.org/2001/XMLSchema" xmlns:xsi="http://www.w3.org/2001/XMLSchema-instance" Label="All Situation Goal Sets BG">
  <Preset Label="GoalSetBeMean" Value="16084" />
  <Preset Label="GoalSetCleanSomething" Value="16086" />
  <Preset Label="GoalSetComplimentFood" Value="16087" />
  <Preset Label="GoalSetDiscussFood" Value="16088" />
  <Preset Label="GoalSetDrinkLess" Value="16089" />
  <Preset Label="GoalSetDrinkMore" Value="16090" />
  <Preset Label="GoalSetEatFood" Value="16092" />
  <Preset Label="GoalSetFlirt" Value="16096" />
  <Preset Label="GoalSetFlirtMore" Value="16097" />
  <Preset Label="GoalSetFlirtTarget" Value="16098" />
  <Preset Label="GoalSetGeneralSocia" Value="16102" />
  <Preset Label="GoalSetIntoNew" Value="16103" />
  <Preset Label="GoalSetIntroduction" Value="16105" />
  <Preset Label="GoalSetJoke" Value="16108" />
  <Preset Label="GoalSetJokeMore" Value="16109" />
  <Preset Label="GoalSetJokeTarget" Value="16110" />
  <Preset Label="GoalSetKiss" Value="16111" />
  <Preset Label="GoalSetMakeOut" Value="16112" />
  <Preset Label="GoalSetMeanMore" Value="16114" />
  <Preset Label="GoalSetSocialFriend" Value="16117" />
  <Preset Label="GoalSetSocialTarget" Value="16118" />
  <Preset Label="GoalSetTease" Value="16120" />
  <Preset Label="GoalSetTeaseMore" Value="16121" />
  <Preset Label="GoalSetTeaseTarget" Value="16122" />
  <Preset Label="GoalSetWoohoo" Value="16126" />
  <Preset Label="GoalSet_Brag" Value="16129" />
  <Preset Label="GoalSet_drink" Value="16134" />
  <Preset Label="GoalSet_Dazed" Value="16135" />
  <Preset Label="GoalSet_party_prep" Value="16141" />
  <Preset Label="GoalSet_Playful" Value="16142" />
  <Preset Label="goalSet_SocialTargetElse" Value="16143" />
  <Preset Label="test_goal_set" Value="16146" />
  <Preset Label="test_goal_set_2" Value="16147" />
  <Preset Label="test_goal_set_3" Value="16148" />
  <Preset Label="test_goal_set_4" Value="16149" />
  <Preset Label="test_goal_set_5" Value="23730" />
  <Preset Label="test_goal_set_6" Value="23733" />
  <Preset Label="goalSet_DinnerParty_Host1" Value="23770" />
  <Preset Label="goalSet_DinnerParty_Host2" Value="23771" />
  <Preset Label="goalSet_DinnerParty_Host1_2" Value="23951" />
  <Preset Label="goalSet_DinnerParty_Host2_2" Value="23952" />
  <Preset Label="goalSet_WeddingHost1" Value="23955" />
  <Preset Label="goalSet_WeddingHost1_2" Value="23956" />
  <Preset Label="goalSet_WeddingCaterer1_2" Value="23957" />
  <Preset Label="goalSet_WeddingCaterer1" Value="23958" />
  <Preset Label="goalSet_WeddingBartender1_2" Value="23959" />
  <Preset Label="goalSet_WeddingBartender1" Value="23960" />
  <Preset Label="goalSet_WeddingGeneral1_2" Value="23961" />
  <Preset Label="goalSet_WeddingGeneral1" Value="23962" />
  <Preset Label="goalSet_WeddingGeneral2_2" Value="23963" />
  <Preset Label="goalSet_WeddingGeneral2" Value="23964" />
  <Preset Label="goalSet_Date1" Value="23974" />
  <Preset Label="goalSet_Date1_2" Value="23975" />
  <Preset Label="goalSet_Date2" Value="23976" />
  <Preset Label="goalSet_Date2_2" Value="23977" />
  <Preset Label="goalSet_DinnerParty_Host1_3" Value="26013" />
  <Preset Label="goalSet_DinnerParty_Guest_1_3" Value="26115" />
  <Preset Label="goalSet_DinnerParty_Guest_2_3" Value="26120" />
  <Preset Label="goalSet_DinnerParty_Guest_3_3" Value="26127" />
  <Preset Label="goalSet_Date1_3" Value="29673" />
  <Preset Label="goalSet_Date2_3" Value="29674" />
  <Preset Label="goalSet_Date2_4" Value="29675" />
  <Preset Label="goalSet_BirthdayParty1_1" Value="32006" />
  <Preset Label="goalSet_BirthdayParty2_1" Value="32007" />
  <Preset Label="goalSet_BirthdayParty3_1" Value="32008" />
  <Preset Label="goalSet_BirthdayParty1_2" Value="32009" />
  <Preset Label="goalSet_BirthdayParty3_2" Value="32010" />
  <Preset Label="goalSet_BirthdayParty2_2" Value="32011" />
  <Preset Label="goalSet_BirthdayPartyEntertainer1" Value="33242" />
  <Preset Label="goalSet_BirthdayPartyEntertainer2" Value="33243" />
  <Preset Label="goalSet_BirthdayBartender1" Value="33246" />
  <Preset Label="goalSet_BirthdayBartender1_2" Value="33247" />
  <Preset Label="goalSet_BirthdayCaterer1" Value="33248" />
  <Preset Label="goalSet_BirthdayCaterer1_2" Value="33249" />
  <Preset Label="goalSet_HousePartyBartender1" Value="33325" />
  <Preset Label="goalSet_HousePartyBartender1_2" Value="33326" />
  <Preset Label="goalSet_HousePartyCaterer1" Value="33327" />
  <Preset Label="goalSet_HousePartyCaterer1_2" Value="33328" />
  <Preset Label="goalSet_HouseParty1_1" Value="33329" />
  <Preset Label="goalSet_HouseParty1_2" Value="33330" />
  <Preset Label="goalSet_HouseParty2_1" Value="33331" />
  <Preset Label="goalSet_HouseParty2_2" Value="33332" />
  <Preset Label="goalSet_HouseParty3_1" Value="33333" />
  <Preset Label="goalSet_HouseParty3_2" Value="33335" />
  <Preset Label="goalSet_HousePartyEntertainer1" Value="33336" />
  <Preset Label="goalSet_HousePartyEntertainer2" Value="33337" />
  <Preset Label="goalSet_DinnerParty_Host3" Value="33447" />
  <Preset Label="goalSet_DinnerParty_Host3_1" Value="33448" />
  <Preset Label="goalSet_BlackAndWhiteParty1_1" Value="37164" />
  <Preset Label="goalSet_BlackAndWhiteParty1_2" Value="37165" />
  <Preset Label="goalSet_BlackAndWhiteParty2_1" Value="37166" />
  <Preset Label="goalSet_BlackAndWhiteParty2_2" Value="37167" />
  <Preset Label="goalSet_BlackAndWhiteParty3_1" Value="37168" />
  <Preset Label="goalSet_BlackAndWhiteParty3_2" Value="37169" />
  <Preset Label="goalSet_CostumeParty1_1" Value="37177" />
  <Preset Label="goalSet_CostumeParty1_2" Value="37178" />
  <Preset Label="goalSet_CostumeParty2_1" Value="37179" />
  <Preset Label="goalSet_CostumeParty2_2" Value="37180" />
  <Preset Label="goalSet_CostumeParty3_1" Value="37181" />
  <Preset Label="goalSet_BlackAndWhitePartyBartender1_3" Value="39275" />
  <Preset Label="goalSet_Date2_2_Teen" Value="76579" />
  <Preset Label="goalSet_Date2_3_Teen" Value="76580" />
  <Preset Label="goalSet_Date2_4_Teen" Value="76582" />
  <Preset Label="test_autosmoke_goal_set" Value="97501" />
  <Preset Label="goalSet_Date_NPC_Invite_1" Value="117096" />
  <Preset Label="goalSet_Date_NPC_Invite_2" Value="117098" />
  <Preset Label="goalSet_PlayDate_NPC_Invite_1" Value="117193" />
  <Preset Label="goalSet_PlayDate_NPC_Invite_2" Value="117195" />
  <Preset Label="goalSet_PlayDate_NPC_Invite_3" Value="117201" />
  <Preset Label="goalSet_Date_NPC_Invite_3" Value="117266" />
  <Preset Label="goalSet_BirthdayParty_NPC_Invite_1" Value="117404" />
  <Preset Label="goalSet_BirthdayParty_NPC_Invite_2" Value="117413" />
  <Preset Label="goalSet_BirthdayParty_NPC_Invite_3" Value="117484" />
  <Preset Label="goalSet_WelcomeWagon_1" Value="119928" />
  <Preset Label="goalSet_WelcomeWagon_2" Value="119929" />
  <Preset Label="goalSet_WelcomeWagon_3" Value="119930" />
  <Preset Label="goalSet_CookOut_Host1_1" Value="300663" />
  <Preset Label="goalSet_CookOut_Host1_2" Value="300664" />
  <Preset Label="goalSet_CookOut_Host1_3" Value="300665" />
  <Preset Label="goalSet_CookOut_Host2_1" Value="300667" />
  <Preset Label="goalSet_CookOut_Host2_2" Value="300668" />
  <Preset Label="goalSet_CookOut_Host2_3" Value="300669" />
  <Preset Label="goalSet_CookOut_Host3_1" Value="300671" />
  <Preset Label="goalSet_CookOut_Host3_2" Value="300672" />
  <Preset Label="goalSet_CookOut_Host3_3" Value="300673" />
  <Preset Label="goalSet_FamilyReunion_1_1" Value="305384" />
  <Preset Label="goalSet_FamilyReunion_1_2" Value="305385" />
  <Preset Label="goalSet_FamilyReunion_1_3" Value="305386" />
  <Preset Label="goalSet_FamilyReunion_2_1" Value="305387" />
  <Preset Label="goalSet_FamilyReunion_3_1" Value="305390" />
  <Preset Label="goalSet_FamilyReunion_3_2" Value="305391" />
  <Preset Label="goalSet_BabyShowerGuest_1_1" Value="308470" />
  <Preset Label="goalSet_BabyShower_2_1" Value="308471" />
  <Preset Label="goalSet_BabyShowerGuest_1_2" Value="308474" />
  <Preset Label="goalSet_BabyShowerHost_1_2" Value="308475" />
  <Preset Label="goalSet_BabyShower_2_2" Value="308476" />
  <Preset Label="goalSet_BabyShowerHost_1_1" Value="308477" />
  <Preset Label="goalSet_BabyShower_2_3" Value="309210" />
  <Preset Label="goalSet_groupWalkingTrail" Value="311515" />
  <Preset Label="goalSet_Sleepover_1_1" Value="311725" />
  <Preset Label="goalSet_Sleepover_1_2" Value="311726" />
  <Preset Label="goalSet_Sleepover_2_1" Value="311727" />
  <Preset Label="goalSet_Sleepover_2_2" Value="311728" />
  <Preset Label="goalSet_Sleepover_3_1" Value="311729" />
  <Preset Label="goalSet_Sleepover_4_1" Value="311730" />
  <Preset Label="goalSet_Sleepover_4_2" Value="311731" />
  <Preset Label="goalSet_PivotalMoment_Money1_1" Value="338199" />
  <Preset Label="goalSet_PivotalMoment_Money2_1" Value="338200" />
  <Preset Label="goalSet_PivotalMoment_Money1_2" Value="338201" />
  <Preset Label="goalSet_PivotalMoment_Money2_2" Value="338202" />
  <Preset Label="goalSet_PivotalMoment_Money3" Value="338203" />
  <Preset Label="goalSet_PivotalMoment_Aspiration1_1" Value="338239" />
  <Preset Label="goalSet_PivotalMoment_Aspiration2_1" Value="338240" />
  <Preset Label="goalSet_PivotalMoment_Aspiration1_2" Value="338241" />
  <Preset Label="goalSet_PivotalMoment_Aspiration3_2" Value="338243" />
  <Preset Label="goalSet_PivotalMoment_Needs_0" Value="338244" />
  <Preset Label="goalSet_PivotalMoment_Needs_1" Value="338245" />
  <Preset Label="goalSet_PivotalMoment_Needs_2" Value="338246" />
  <Preset Label="goalSet_PivotalMoment_Needs_3" Value="338247" />
  <Preset Label="goalSet_PivotalMoment_Needs_4" Value="338248" />
  <Preset Label="goalSet_PivotalMoment_Needs_5" Value="338249" />
  <Preset Label="goalSet_PivotalMoment_Needs_6" Value="338250" />
  <Preset Label="goalSet_PivotalMoment_Phone_0" Value="338251" />
  <Preset Label="goalSet_PivotalMoment_Phone_1" Value="338252" />
  <Preset Label="goalSet_PivotalMoment_Phone_2" Value="338253" />
  <Preset Label="goalSet_PivotalMoment_Phone_3" Value="338254" />
  <Preset Label="goalSet_PivotalMoment_Phone_4" Value="338255" />
  <Preset Label="goalSet_PivotalMoment_Skill_0" Value="338256" />
  <Preset Label="goalSet_PivotalMoment_Skill_1" Value="338257" />
  <Preset Label="goalSet_PivotalMoment_Skill_2" Value="338258" />
  <Preset Label="goalSet_PivotalMoment_Skill_3" Value="338259" />
  <Preset Label="goalSet_PivotalMoment_SocialAndTravel1" Value="338260" />
  <Preset Label="goalSet_PivotalMoment_SocialAndTravel2_1" Value="338261" />
  <Preset Label="goalSet_PivotalMoment_SocialAndTravel2_2" Value="338262" />
  <Preset Label="goalSet_PivotalMoment_SocialAndTravel1_2" Value="357645" />
  <Preset Label="goalSet_R3Event_Quest01_0" Value="377906" />
  <Preset Label="goalSet_R3Event_Quest01_1" Value="377907" />
  <Preset Label="goalSet_R3Event_Quest01_2" Value="377908" />
  <Preset Label="goalSet_R3Event_Quest01_3" Value="378247" />
  <Preset Label="goalSet_R3Event_Quest02_0" Value="378824" />
  <Preset Label="goalSet_R3Event_Quest02_0_1_1" Value="378825" />
  <Preset Label="goalSet_R3Event_Quest02_0_1" Value="378828" />
  <Preset Label="goalSet_R3Event_Quest02_1" Value="378829" />
  <Preset Label="goalSet_R3Event_Quest02_2_1_1" Value="378830" />
  <Preset Label="goalSet_R3Event_Quest02_2_1" Value="378831" />
  <Preset Label="goalSet_R3Event_Quest03_0" Value="378890" />
  <Preset Label="goalSet_R3Event_Quest03_1" Value="378891" />
  <Preset Label="goalSet_R3Event_Quest03_2" Value="378892" />
  <Preset Label="goalSet_R3Event_Quest03_0_1" Value="378893" />
  <Preset Label="goalSet_R3Event_Quest04_1" Value="379127" />
  <Preset Label="goalSet_R3Event_Quest04_2" Value="379128" />
  <Preset Label="goalSet_R3Event_Quest04_3" Value="379129" />
  <Preset Label="goalSet_R3Event_Quest04_2_1" Value="379180" />
  <Preset Label="goalSet_R3Event_Quest04_2_1_1" Value="379181" />
  <Preset Label="goalSet_R3Event_Quest04_2_1_2" Value="379182" />
  <Preset Label="goalSet_R3Event_Quest05_0" Value="379183" />
  <Preset Label="goalSet_R3Event_Quest05_0_1" Value="379184" />
  <Preset Label="goalSet_R3Event_Quest05_0_1_1" Value="379185" />
  <Preset Label="goalSet_R3Event_Quest06_0" Value="379208" />
  <Preset Label="goalSet_R3Event_Quest06_1" Value="379209" />
  <Preset Label="goalSet_R3Event_Quest06_0_1" Value="379216" />
  <Preset Label="goalSet_R3Event_Quest06_0_1_1" Value="379217" />
  <Preset Label="goalSet_R3Event_Quest07_0" Value="379272" />
  <Preset Label="goalSet_R3Event_Quest07_1" Value="379273" />
  <Preset Label="goalSet_R3Event_Quest07_0_1" Value="379274" />
  <Preset Label="goalSet_R3Event_Quest08_0" Value="379277" />
  <Preset Label="goalSet_R3Event_Quest08_1" Value="379278" />
  <Preset Label="goalSet_R3Event_Quest08_0_1" Value="379279" />
  <Preset Label="goalSet_R3Event_Quest08_0_1_1" Value="379280" />
  <Preset Label="goalSet_R3Event_Quest08_0_1_2" Value="379281" />
  <Preset Label="goalSet_R3Event_Quest08_0_1_3" Value="379282" />
  <Preset Label="goalSet_R3Event_Quest09_0" Value="379286" />
  <Preset Label="goalSet_R3Event_Quest09_1" Value="379287" />
  <Preset Label="goalSet_R3Event_Quest10_0" Value="379607" />
  <Preset Label="goalSet_R3Event_Quest10_0_1" Value="379608" />
  <Preset Label="goalSet_R3Event_Quest10_0_1_1" Value="379609" />
  <Preset Label="goalSet_R3Event_Quest10_0_1_2" Value="379610" />
  <Preset Label="goalSet_R3Event_Quest11_0" Value="380019" />
  <Preset Label="goalSet_R3Event_Quest11_0_1" Value="380020" />
  <Preset Label="goalSet_R3Event_Quest11_0_1_1" Value="380021" />
  <Preset Label="goalSet_R3Event_Quest12_0" Value="380024" />
  <Preset Label="goalSet_R3Event_Quest12_0_1" Value="380025" />
  <Preset Label="goalSet_R3Event_Quest03_0_1_1" Value="381882" />
  <Preset Label="goalSet_R3Event_Quest05_0_1_1_1" Value="395520" />
  <Preset Label="goalSet_R3Event_Quest01_4" Value="395522" />
  <Preset Label="goalSet_R3Event_Quest01_3_1" Value="395751" />
  <Preset Label="goalSet_R3Event_Quest03_0_1_2" Value="395754" />
  <Preset Label="goalSet_R3Event_Quest04_2_1_3" Value="395756" />
  <Preset Label="goalSet_R3Event_Quest10_0_1_3" Value="395763" />
  <Preset Label="goalSet_R3Event_Quest01_4_0" Value="395844" />
  <Preset Label="goalSet_HobbyClass_Social_2" Value="396733" />
  <Preset Label="goalSet_HobbyClass_Social_3" Value="396932" />
  <Preset Label="goalSet_HobbyClass_Confident_1" Value="396947" />
  <Preset Label="goalSet_HobbyClass_Energized_1" Value="396948" />
  <Preset Label="goalSet_HobbyClass_Flirty_1" Value="396949" />
  <Preset Label="goalSet_HobbyClass_Focused_1" Value="396950" />
  <Preset Label="goalSet_HobbyClass_Inspired_1" Value="396951" />
  <Preset Label="goalSet_HobbyClass_Playful_1" Value="396952" />
  <Preset Label="goalSet_HobbyClass_Confident_2" Value="396953" />
  <Preset Label="goalSet_HobbyClass_Energized_2" Value="396954" />
  <Preset Label="goalSet_HobbyClass_Flirty_2" Value="396955" />
  <Preset Label="goalSet_HobbyClass_Focused_2" Value="396956" />
  <Preset Label="goalSet_HobbyClass_Inspired_2" Value="396957" />
  <Preset Label="goalSet_HobbyClass_Playful_2" Value="396958" />
  <Preset Label="goalSet_R3Event_Quest04_4" Value="397168" />
  <Preset Label="goalSet_R4Event_Quest01_0" Value="404826" />
  <Preset Label="goalSet_R4Event_Quest01_1" Value="404827" />
  <Preset Label="goalSet_R4Event_Quest02_0" Value="410958" />
  <Preset Label="goalSet_R4Event_Quest03_0" Value="410959" />
  <Preset Label="goalSet_R4Event_Quest04_0" Value="410960" />
  <Preset Label="goalSet_R4Event_Quest05_0" Value="410961" />
  <Preset Label="goalSet_R4Event_Quest06_0" Value="410962" />
  <Preset Label="goalSet_R4Event_Quest07_0" Value="410963" />
  <Preset Label="goalSet_R4Event_Quest08_0" Value="410964" />
  <Preset Label="goalSet_R4Event_Quest02_1" Value="423842" />
  <Preset Label="goalSet_R4Event_Quest03_1" Value="423843" />
  <Preset Label="goalSet_R4Event_Quest01_2" Value="423845" />
  <Preset Label="goalSet_R4Event_Quest01_3" Value="423866" />
  <Preset Label="goalSet_R4Event_Quest05_1" Value="423867" />
  <Preset Label="goalSet_R4Event_Quest05_2" Value="423886" />
  <Preset Label="goalSet_R4Event_Quest01_4" Value="424151" />
  <Preset Label="goalSet_R4Event_Quest01_5" Value="424152" />
  <Preset Label="goalSet_R4Event_Quest02_2" Value="424405" />
  <Preset Label="goalSet_R4Event_Quest02_3" Value="424406" />
  <Preset Label="goalSet_R4Event_Quest02_4" Value="424407" />
  <Preset Label="goalSet_R4Event_Quest06_1" Value="424732" />
  <Preset Label="goalSet_R4Event_Quest07_1" Value="424973" />
  <Preset Label="goalSet_R4Event_Quest07_2" Value="424974" />
  <Preset Label="goalSet_R4Event_Quest07_3" Value="424975" />
  <Preset Label="goalSet_R4Event_Quest08_1" Value="425006" />
  <Preset Label="goalSet_R4Event_Quest04_1" Value="425009" />
  <Preset Label="goalSet_R4Event_Quest04_2" Value="425010" />
  <Preset Label="goalSet_R4Event_Quest04_3" Value="425011" />
  <Preset Label="goalSet_DecemberEvent_Quest01_0" Value="425823" />
  <Preset Label="goalSet_DecemberEvent_Quest01_0_1" Value="425874" />
  <Preset Label="goalSet_DecemberEvent_Quest01_1" Value="425875" />
  <Preset Label="goalSet_DecemberEvent_Quest02_0" Value="426379" />
  <Preset Label="goalSet_DecemberEvent_Quest02_1" Value="426380" />
  <Preset Label="goalSet_DecemberEvent_Quest02_1_1" Value="426381" />
  <Preset Label="goalSet_DecemberEvent_Quest03_0" Value="426382" />
  <Preset Label="goalSet_DecemberEvent_Quest03_1" Value="426383" />
  <Preset Label="goalSet_DecemberEvent_Quest03_1_0" Value="426384" />
  <Preset Label="goalSet_DecemberEvent_Quest04_0" Value="426385" />
  <Preset Label="goalSet_DecemberEvent_Quest04_0_1" Value="426386" />
  <Preset Label="goalSet_DecemberEvent_Quest04_1" Value="426387" />
  <Preset Label="goalSet_DecemberEvent_Quest04_1_1" Value="426388" />
  <Preset Label="goalSet_DecemberEvent_Quest05_0" Value="426399" />
  <Preset Label="goalSet_DecemberEvent_Quest05_1" Value="426400" />
  <Preset Label="goalSet_DecemberEvent_Quest05_0_1" Value="426401" />
  <Preset Label="goalSet_DecemberEvent_Quest05_1_1" Value="426402" />
  <Preset Label="goalSet_DecemberEvent_Quest06_0" Value="426403" />
  <Preset Label="goalSet_DecemberEvent_Quest06_1" Value="426404" />
  <Preset Label="goalSet_DecemberEvent_Quest06_0_1" Value="426405" />
  <Preset Label="goalSet_DecemberEvent_Quest06_1_1" Value="426406" />
  <Preset Label="goalSet_DecemberEvent_Quest06_1_2" Value="426407" />
  <Preset Label="goalSet_R4Event_Quest01_6" Value="428854" />
  <Preset Label="goalSet_R4Event_Quest02_5" Value="428903" />
  <Preset Label="goalSet_R4Event_Quest02_6" Value="428904" />
  <Preset Label="goalSet_R4Event_Quest03_0_1" Value="430359" />
  <Preset Label="goalSet_R4Event_Quest03_1_1" Value="430361" />
  <Preset Label="goalSet_R4Event_Quest03_1_2" Value="430362" />
  <Preset Label="goalSet_R4Event_Quest03_1_3" Value="430363" />
  <Preset Label="goalSet_R4Event_Quest03_1_4" Value="430364" />
  <Preset Label="goalSet_R4Event_Quest04_6" Value="430529" />
  <Preset Label="goalSet_R4Event_Quest04_4" Value="430535" />
  <Preset Label="goalSet_R4Event_Quest04_5" Value="430536" />
  <Preset Label="goalSet_R4Event_Quest05_0_1" Value="431262" />
  <Preset Label="goalSet_R4Event_Quest05_0_1_1" Value="431263" />
  <Preset Label="goalSet_R4Event_Quest05_0_1_1_1" Value="431264" />
  <Preset Label="goalSet_R4Event_Quest05_1_Hidden" Value="431265" />
  <Preset Label="goalSet_R4Event_Quest05_2_Hidden" Value="431266" />
  <Preset Label="goalSet_PivotalMoment_Exploration_0_N3" Value="431339" />
  <Preset Label="goalSet_PivotalMoment_Aspiration_2_1_N3" Value="431340" />
  <Preset Label="goalSet_PivotalMoment_Aspiration_2_2_N3" Value="431341" />
  <Preset Label="goalSet_PivotalMoment_Needs_3_N3" Value="431351" />
  <Preset Label="goalSet_R5Event_Quest01_0" Value="438029" />
  <Preset Label="goalSet_R5Event_Quest01_0_1" Value="438329" />
  <Preset Label="goalSet_R5Event_Quest01_0_1_1" Value="438330" />
  <Preset Label="goalSet_R5Event_Quest01_1" Value="438331" />
  <Preset Label="goalSet_R5Event_Quest02_0" Value="438339" />
  <Preset Label="goalSet_R5Event_Quest02_1" Value="438340" />
  <Preset Label="goalSet_R5Event_Quest02_1_1" Value="438341" />
  <Preset Label="goalSet_R5Event_Quest02_2" Value="438342" />
  <Preset Label="goalSet_R5Event_Quest02_3" Value="438343" />
  <Preset Label="goalSet_R5Event_Quest03_0" Value="438344" />
  <Preset Label="goalSet_R5Event_Quest03_1" Value="438345" />
  <Preset Label="goalSet_R5Event_Quest03_1_1" Value="438346" />
  <Preset Label="goalSet_R5Event_Quest03_1_2" Value="438347" />
  <Preset Label="goalSet_R5Event_Quest03_2" Value="438348" />
  <Preset Label="goalSet_R5Event_Quest03_2_1" Value="438349" />
  <Preset Label="goalSet_R5Event_Quest04_0" Value="438350" />
  <Preset Label="goalSet_R5Event_Quest04_1" Value="438351" />
  <Preset Label="goalSet_R5Event_Quest04_0_1" Value="438352" />
  <Preset Label="goalSet_R5Event_Quest04_2" Value="438353" />
  <Preset Label="goalSet_R5Event_Quest05_0" Value="438359" />
  <Preset Label="goalSet_R5Event_Quest05_1" Value="438360" />
  <Preset Label="goalSet_R5Event_Quest05_1_1" Value="438361" />
  <Preset Label="goalSet_R5Event_Quest05_1_1_1_1" Value="438363" />
  <Preset Label="goalSet_R5Event_Quest05_1_1_1_1_1" Value="438364" />
  <Preset Label="goalSet_R5Event_Quest06_0" Value="438365" />
  <Preset Label="goalSet_R5Event_Quest06_1" Value="438366" />
  <Preset Label="goalSet_R5Event_Quest06_2" Value="438367" />
  <Preset Label="goalSet_R5Event_Quest06_3" Value="438368" />
  <Preset Label="goalSet_R5Event_Quest07_0" Value="438379" />
  <Preset Label="goalSet_R5Event_Quest07_0_1" Value="438380" />
  <Preset Label="goalSet_R5Event_Quest07_1" Value="438381" />
  <Preset Label="goalSet_R5Event_Quest07_2" Value="438382" />
  <Preset Label="goalSet_R5Event_Quest08_0" Value="438386" />
  <Preset Label="goalSet_R5Event_Quest08_1" Value="438387" />
  <Preset Label="goalSet_R5Event_Quest08_1_1" Value="438388" />
  <Preset Label="goalSet_PivotalMoment_DreamsV0_N5_Narrative_choice1_A1" Value="439921" />
  <Preset Label="goalSet_PivotalMoment_DreamsV0_N5_Narrative_choice1_A2" Value="439922" />
  <Preset Label="goalSet_PivotalMoment_DreamsV0_N5_Narrative_choice1_A3" Value="439923" />
  <Preset Label="goalSet_PivotalMoment_DreamsV0_N5_Narrative_choice1_A4" Value="439924" />
  <Preset Label="goalSet_PivotalMoment_DreamsV0_N5_Narrative_choice1_A5" Value="439925" />
  <Preset Label="goalSet_PivotalMoment_DreamsV0_N5_Narrative_choice1_A6" Value="439926" />
  <Preset Label="goalSet_PivotalMoment_DreamsV0_N5_Narrative_choice1_B1" Value="440409" />
  <Preset Label="goalSet_PivotalMoment_DreamsV0_N5_Narrative_choice1_B2" Value="440410" />
  <Preset Label="goalSet_PivotalMoment_DreamsV0_N5_Narrative_choice1_B3" Value="440411" />
  <Preset Label="goalSet_PivotalMoment_DreamsV0_N5_Narrative_choice1_B4" Value="440412" />
  <Preset Label="goalSet_PivotalMoment_DreamsV0_N5_Narrative_choice1_B5" Value="440413" />
  <Preset Label="goalSet_PivotalMoment_DreamsV0_N5_Narrative_choice1_B6" Value="440414" />
  <Preset Label="goalSet_PivotalMoment_DreamsV0_N5_Narrative_choice1_C1" Value="440970" />
  <Preset Label="goalSet_PivotalMoment_DreamsV0_N5_Narrative_choice1_C2" Value="440971" />
  <Preset Label="goalSet_PivotalMoment_DreamsV0_N5_Narrative_choice1_C3" Value="440972" />
  <Preset Label="goalSet_PivotalMoment_DreamsV0_N5_Narrative_choice1_C4" Value="440973" />
  <Preset Label="goalSet_PivotalMoment_DreamsV0_N5_Narrative_choice1_C5" Value="440974" />
  <Preset Label="goalSet_PivotalMoment_DreamsV0_N5_Narrative_choice1_C6" Value="440975" />
  <Preset Label="goalSet_PivotalMoment_DreamsV0_N5_Narrative_choice2_A1" Value="442769" />
  <Preset Label="goalSet_PivotalMoment_DreamsV0_N5_Narrative_choice2_A2" Value="442770" />
  <Preset Label="goalSet_PivotalMoment_DreamsV0_N5_Narrative_choice2_A3" Value="442771" />
  <Preset Label="goalSet_PivotalMoment_DreamsV0_N5_Narrative_choice2_A4" Value="442772" />
  <Preset Label="goalSet_PivotalMoment_DreamsV0_N5_Narrative_choice2_A5" Value="442773" />
  <Preset Label="goalSet_PivotalMoment_DreamsV0_N5_Narrative_choice2_B1" Value="442774" />
  <Preset Label="goalSet_PivotalMoment_DreamsV0_N5_Narrative_choice2_B2" Value="442775" />
  <Preset Label="goalSet_PivotalMoment_DreamsV0_N5_Narrative_choice2_B3" Value="442776" />
  <Preset Label="goalSet_PivotalMoment_DreamsV0_N5_Narrative_choice2_B4" Value="442777" />
  <Preset Label="goalSet_PivotalMoment_DreamsV0_N5_Narrative_choice2_B5" Value="442778" />
  <Preset Label="goalSet_PivotalMoment_DreamsV0_N5_Narrative_choice2_C1" Value="442779" />
  <Preset Label="goalSet_PivotalMoment_DreamsV0_N5_Narrative_choice2_C2" Value="442780" />
  <Preset Label="goalSet_PivotalMoment_DreamsV0_N5_Narrative_choice2_C3" Value="442781" />
  <Preset Label="goalSet_PivotalMoment_DreamsV0_N5_Narrative_choice2_C4" Value="442782" />
  <Preset Label="goalSet_PivotalMoment_DreamsV0_N5_Narrative_choice2_C5" Value="442783" />
  <Preset Label="goalSet_PivotalMoment_DreamsV0_N5_General_choice1_A1" Value="445462" />
  <Preset Label="goalSet_PivotalMoment_DreamsV0_N5_General_choice1_A2" Value="445463" />
  <Preset Label="goalSet_PivotalMoment_DreamsV0_N5_General_choice1_A3" Value="445464" />
  <Preset Label="goalSet_PivotalMoment_DreamsV0_N5_General_choice1_A4" Value="445465" />
  <Preset Label="goalSet_PivotalMoment_DreamsV0_N5_General_choice1_A5" Value="445466" />
  <Preset Label="goalSet_PivotalMoment_DreamsV0_N5_General_choice1_A6" Value="445467" />
  <Preset Label="goalSet_PivotalMoment_DreamsV0_N5_General_choice1_B1" Value="445468" />
  <Preset Label="goalSet_PivotalMoment_DreamsV0_N5_General_choice1_B2" Value="445469" />
  <Preset Label="goalSet_PivotalMoment_DreamsV0_N5_General_choice1_B3" Value="445470" />
  <Preset Label="goalSet_PivotalMoment_DreamsV0_N5_General_choice1_B4" Value="445471" />
  <Preset Label="goalSet_PivotalMoment_DreamsV0_N5_General_choice1_B5" Value="445472" />
  <Preset Label="goalSet_PivotalMoment_DreamsV0_N5_General_choice1_B6" Value="445473" />
  <Preset Label="goalSet_PivotalMoment_DreamsV0_N5_General_choice1_C1" Value="445474" />
  <Preset Label="goalSet_PivotalMoment_DreamsV0_N5_General_choice1_C2" Value="445475" />
  <Preset Label="goalSet_PivotalMoment_DreamsV0_N5_General_choice1_C3" Value="445476" />
  <Preset Label="goalSet_PivotalMoment_DreamsV0_N5_General_choice1_C4" Value="445477" />
  <Preset Label="goalSet_PivotalMoment_DreamsV0_N5_General_choice1_C5" Value="445478" />
  <Preset Label="goalSet_PivotalMoment_DreamsV0_N5_General_choice1_C6" Value="445479" />
  <Preset Label="goalSet_R5Event_Quest07_2_1" Value="445757" />
  <Preset Label="goalSet_R5Event_Quest07_2_2" Value="445758" />
  <Preset Label="goalSet_R5Event_Quest07_2_3" Value="445759" />
  <Preset Label="goalSet_PivotalMoment_DreamsV0_N5_General_choice2_A1" Value="446057" />
  <Preset Label="goalSet_PivotalMoment_DreamsV0_N5_General_choice2_A2" Value="446058" />
  <Preset Label="goalSet_PivotalMoment_DreamsV0_N5_General_choice2_A3" Value="446059" />
  <Preset Label="goalSet_PivotalMoment_DreamsV0_N5_General_choice2_A4" Value="446060" />
  <Preset Label="goalSet_PivotalMoment_DreamsV0_N5_General_choice2_A5" Value="446061" />
  <Preset Label="goalSet_PivotalMoment_DreamsV0_N5_General_choice2_A6" Value="446062" />
  <Preset Label="goalSet_PivotalMoment_DreamsV0_N5_General_choice2_B1" Value="446063" />
  <Preset Label="goalSet_PivotalMoment_DreamsV0_N5_General_choice2_B2" Value="446064" />
  <Preset Label="goalSet_PivotalMoment_DreamsV0_N5_General_choice2_B3" Value="446065" />
  <Preset Label="goalSet_PivotalMoment_DreamsV0_N5_General_choice2_B4" Value="446066" />
  <Preset Label="goalSet_PivotalMoment_DreamsV0_N5_General_choice2_B5" Value="446067" />
  <Preset Label="goalSet_PivotalMoment_DreamsV0_N5_General_choice2_B6" Value="446068" />
  <Preset Label="goalSet_PivotalMoment_DreamsV0_N5_General_choice2_C1" Value="446069" />
  <Preset Label="goalSet_PivotalMoment_DreamsV0_N5_General_choice2_C2" Value="446070" />
  <Preset Label="goalSet_PivotalMoment_DreamsV0_N5_General_choice2_C3" Value="446071" />
  <Preset Label="goalSet_PivotalMoment_DreamsV0_N5_General_choice2_C4" Value="446072" />
  <Preset Label="goalSet_PivotalMoment_DreamsV0_N5_General_choice2_C5" Value="446073" />
  <Preset Label="goalSet_PivotalMoment_DreamsV0_N5_General_choice2_C6" Value="446074" />
  <Preset Label="goalSet_PivotalMoment_dreamsV0_N5_DLC_Quest_A1" Value="446612" />
  <Preset Label="goalSet_PivotalMoment_dreamsV0_N5_DLC_Quest_A2" Value="446613" />
  <Preset Label="goalSet_PivotalMoment_dreamsV0_N5_DLC_Quest_B1" Value="446614" />
  <Preset Label="goalSet_PivotalMoment_dreamsV0_N5_DLC_Quest_B2" Value="446615" />
  <Preset Label="goalSet_PivotalMoment_dreamsV0_N5_DLC_Quest_C1" Value="446616" />
  <Preset Label="goalSet_R5Event_Quest01_2" Value="448096" />
  <Preset Label="goalSet_R5Event_Quest03_3" Value="448167" />
  <Preset Label="goalSet_R5Event_Quest04_3" Value="448177" />
  <Preset Label="goalSet_R5Event_Quest07_3" Value="448457" />
  <Preset Label="goalSet_R5Event_Quest04_3_1" Value="449467" />
  <Preset Label="goalSet_R5Event_Quest01_2_1" Value="449470" />
  <Preset Label="goalSet_R5Event_Quest03_3_1" Value="450244" />
  <Preset Label="goalSet_R5Event_Quest07_3_1" Value="450250" />
</PresetGroup>