<?xml version="1.0"?>
<PresetGroup xmlns:xsd="http://www.w3.org/2001/XMLSchema" xmlns:xsi="http://www.w3.org/2001/XMLSchema-instance" Label="All Buffs FP01">
  <Preset Label="Frayed Nerves (buff_HolidayCracker_Stressed_elders)" Value="154614" />
  <Preset Label="Crinkle. Whiz. Pop! (buff_HolidayCracker_PlayfulBuff)" Value="154615" />
  <Preset Label="Feeling Festive (buff_HolidayCracker_FestiveBuff)" Value="154617" />
  <Preset Label="Bah, Humbug! (buff_HolidayCracker_ChildAngerBuff)" Value="154618" />
  <Preset Label="Broken Dreams (buff_HolidayCracker_SadBuff)" Value="154619" />
  <Preset Label="Secret Sweets: Spicy-Hot (buff_HolidayCracker_CandyBuffs_Flirty)" Value="155065" />
  <Preset Label="Secret Sweets: Fizz (buff_HolidayCracker_CandyBuffs_Dazed)" Value="155089" />
  <Preset Label="Secret Sweets: Sugar-Bomb (buff_HolidayCracker_CandyBuffs_Energized)" Value="155102" />
  <Preset Label="Secret Sweets: Caramel (buff_HolidayCracker_CandyBuffs_Happy)" Value="155103" />
  <Preset Label="Secret Sweets: Taffy (buff_HolidayCracker_CandyBuffs_Playful)" Value="155104" />
  <Preset Label="Secret Sweets: Sour (buff_HolidayCracker_CandyBuffs_Uncomfortable)" Value="155107" />
  <Preset Label="Rudely Awoken (buff_Sim_WokeUp_notLazy)" Value="155804" />
  <Preset Label="Startling Sound (buff_HolidayCracker_Stressed)" Value="156177" />
</PresetGroup>