<?xml version="1.0"?>
<PresetGroup xmlns:xsd="http://www.w3.org/2001/XMLSchema" xmlns:xsi="http://www.w3.org/2001/XMLSchema-instance" Label="All Interaction Lists EP01">
  <Preset Label="affordanceList_socialMixers_InterrogationTable" Value="103587" />
  <Preset Label="al_ChemistryTable_Crafting_Actions" Value="105303" />
  <Preset Label="al_ChemistryTable_Experiment_Actions" Value="105407" />
  <Preset Label="affordanceList_HospitalExamBed_Seated_Examine" Value="107998" />
  <Preset Label="affordanceList_SurgeryTable_TreatmentMixers" Value="110485" />
  <Preset Label="affordanceList_RetailMannequin" Value="110555" />
  <Preset Label="socialMixers_Retail_NonTouching" Value="112376" />
  <Preset Label="socialMixers_Retail_Touching" Value="112377" />
  <Preset Label="social_Mixers_ScienceCareer" Value="113518" />
  <Preset Label="affordanceList_HospitalTreadmill_mixers_Success" Value="115706" />
  <Preset Label="affordanceList_HospitalTreadmill_mixers_Fail" Value="115707" />
</PresetGroup>